blivedm/__init__.py
blivedm/handlers.py
blivedm/utils.py
blivedm/clients/__init__.py
blivedm/clients/open_live.py
blivedm/clients/web.py
blivedm/clients/ws_base.py
blivedm/models/__init__.py
blivedm/models/open_live.py
blivedm/models/web.py
laplace_blivedm-0.0.6.dist-info/METADATA
laplace_blivedm-0.0.6.dist-info/WHEEL
laplace_blivedm-0.0.6.dist-info/licenses/LICENSE
laplace_blivedm-0.0.6.dist-info/RECORD
